evidence_ext/__init__.py
evidence_ext/config.py
evidence_ext/extension.py
evidence_ext/main.py
evidence_ext-0.7.0.dist-info/LICENSE
evidence_ext-0.7.0.dist-info/METADATA
evidence_ext-0.7.0.dist-info/WHEEL
evidence_ext-0.7.0.dist-info/entry_points.txt
evidence_ext-0.7.0.dist-info/RECORD
