Metadata-Version: 2.1
Name: evidence-ext
Version: 0.7.0
Summary: `evidence-ext` is a Meltano utility extension.
License: Apache-2.0
Author: Meltano
Author-email: hello@meltano.com
Requires-Python: >=3.8,<4
Classifier: License :: OSI Approved :: Apache Software License
Classifier: Programming Language :: Python :: 3
Classifier: Programming Language :: Python :: 3.8
Classifier: Programming Language :: Python :: 3.9
Classifier: Programming Language :: Python :: 3.10
Classifier: Programming Language :: Python :: 3.11
Classifier: Programming Language :: Python :: 3.12
Requires-Dist: PyYAML (>=6.0.0,<7.0.0)
Requires-Dist: click (>=8.1.3,<9.0.0)
Requires-Dist: meltano.edk (>=0.4.0,<0.5.0)
Requires-Dist: nodejs-bin[cmd] (>=18.4.0a4,<19.0.0)
Requires-Dist: typer (>=0.6.1,<0.10.0)
